functions_by_olgabotnari/README.md
functions_by_olgabotnari/math_functions.py
functions_by_olgabotnari-0.3.0.dist-info/WHEEL
functions_by_olgabotnari-0.3.0.dist-info/METADATA
functions_by_olgabotnari-0.3.0.dist-info/RECORD
